[
  { "id": 1,
   "uri": "https://picsum.photos/id/237/400/300" 
  },
  { "id": 2,
   "uri": "https://picsum.photos/id/238/400/300" 
  },
  { "id": 3, 
  "uri": "https://picsum.photos/id/239/400/300"
 },
  { "id": 4, 
  "uri": "https://picsum.photos/id/240/400/300" 
},
  { "id": 5, 
  "uri": "https://picsum.photos/id/241/400/300"
 },
  { "id": 6, 
  "uri": "https://picsum.photos/id/242/400/300" 
},
  { "id": 7, 
  "uri": "https://picsum.photos/id/243/400/300" 
},
  { "id": 8, 
  "uri": "https://picsum.photos/id/244/400/300"
 },
  { "id": 9, 
  "uri": "https://picsum.photos/id/245/400/300"
},
  { "id": 10, "uri":
   "https://picsum.photos/id/246/400/300"
 },
  { "id": 11, "uri":
   "https://picsum.photos/id/247/400/300"
 },
  { "id": 12, "uri":
   "https://picsum.photos/id/248/400/300"
 },
  { "id": 13, "uri":
   "https://picsum.photos/id/249/400/300"
 },
  { "id": 14, "uri":
   "https://picsum.photos/id/250/400/300"
 },
  { "id": 15, "uri":
   "https://picsum.photos/id/251/400/300"
 },
  { "id": 16, "uri":
   "https://picsum.photos/id/252/400/300"
 },
  { "id": 17, "uri":
   "https://picsum.photos/id/253/400/300"
 },
  { "id": 18, "uri":
   "https://picsum.photos/id/254/400/300"
 },
  { "id": 19, "uri":
   "https://picsum.photos/id/255/400/300"
 },
  { "id": 20, "uri":
   "https://picsum.photos/id/257/400/300"
 }
]
